ares/__init__.py
ares/__init__.pyc
ares/ares.py
ares/binary_classifier.py
ares/kilt_filter.py
ares/label_filter.py
ares/prompts.py
ares/rag_scoring.py
ares/superglue_filter.py
ares/synthetic_generator.py
ares/ues_idp.py
ares/LLM_as_a_Judge_Adaptation/Filter_Synthetic_Queries.py
ares/LLM_as_a_Judge_Adaptation/General_Binary_Classifier.py
ares/LLM_as_a_Judge_Adaptation/Generate_Synthetic_Queries_and_Answers.py
ares/LLM_as_a_Judge_Adaptation/LLM_Generation_Functions.py
ares/LLM_as_a_Judge_Adaptation/LLM_Synthetic_Generation.py
ares/LLM_as_a_Judge_Adaptation/__init__.py
ares/LLM_as_a_Judge_Adaptation/pytorchtools.py
ares/LLM_as_a_Judge_Adaptation/__pycache__/Filter_Synthetic_Queries.cpython-310.pyc
ares/LLM_as_a_Judge_Adaptation/__pycache__/Filter_Synthetic_Queries.cpython-311.pyc
ares/LLM_as_a_Judge_Adaptation/__pycache__/General_Binary_Classifier.cpython-310.pyc
ares/LLM_as_a_Judge_Adaptation/__pycache__/General_Binary_Classifier.cpython-311.pyc
ares/LLM_as_a_Judge_Adaptation/__pycache__/Generate_Synthetic_Queries_and_Answers.cpython-310.pyc
ares/LLM_as_a_Judge_Adaptation/__pycache__/Generate_Synthetic_Queries_and_Answers.cpython-311.pyc
ares/LLM_as_a_Judge_Adaptation/__pycache__/LLM_Generation_Functions.cpython-310.pyc
ares/LLM_as_a_Judge_Adaptation/__pycache__/LLM_Generation_Functions.cpython-311.pyc
ares/LLM_as_a_Judge_Adaptation/__pycache__/LLM_Synthetic_Generation.cpython-310.pyc
ares/LLM_as_a_Judge_Adaptation/__pycache__/__init__.cpython-310.pyc
ares/LLM_as_a_Judge_Adaptation/__pycache__/__init__.cpython-311.pyc
ares/LLM_as_a_Judge_Adaptation/__pycache__/pytorchtools.cpython-310.pyc
ares/RAG_Automatic_Evaluation/Evaluation_Functions.py
ares/RAG_Automatic_Evaluation/LLMJudge_RAG_Compared_Scoring.py
ares/RAG_Automatic_Evaluation/Prepare_FinanceBench.py
ares/RAG_Automatic_Evaluation/Prepare_KILT_Dataset.py
ares/RAG_Automatic_Evaluation/Prepare_SuperGLUE_Datasets.py
ares/RAG_Automatic_Evaluation/__init__.py
ares/RAG_Automatic_Evaluation/ppi.py
ares/ares_ai.egg-info/PKG-INFO
ares/ares_ai.egg-info/SOURCES.txt
ares/ares_ai.egg-info/dependency_links.txt
ares/ares_ai.egg-info/entry_points.txt
ares/ares_ai.egg-info/requires.txt
ares/ares_ai.egg-info/top_level.txt
ares_ai-0.6.6.dist-info/LICENSE
ares_ai-0.6.6.dist-info/METADATA
ares_ai-0.6.6.dist-info/WHEEL
ares_ai-0.6.6.dist-info/entry_points.txt
ares_ai-0.6.6.dist-info/top_level.txt
ares_ai-0.6.6.dist-info/RECORD
