Metadata-Version: 2.1
Name: ares-ai
Version: 0.6.6
Summary: ARES is an advanced evaluation framework for Retrieval-Augmented Generation (RAG) systems, 
Author-email: Jon Saad-Falcon <jonsaadfalcon@stanford.edu>, Robby Manihani <manihani@stanford.edu>, Omar Khattab <okhattab@stanford.edu>, Christopher Potts <cgpotts@stanford.edu>, Matei Zaharia <matei@berkeley.edu>
License: Apache License
Project-URL: documentation, https://github.com/stanford-futuredata/ARES/tree/new-dev/docs
Project-URL: repository, https://github.com/stanford-futuredata/ARES/tree/main
Project-URL: changelog, https://github.com/stanford-futuredata/ARES/blob/new-dev/CHANGELOG.md
Keywords: RAG,RAG Scoring,RAG Systems,Automated Evaluation Framework,Retrieval-Augmented Generation Systems,LLM Judges,Natural Language Processing,Machine Learning,RAG Evaluation,Context Relevance,Answer Faithfulness,Answer Relevance,Synthetic Queries,Synthetic Answers,In-Domain Passages,Key Performance Metrics,Human Preference Validation Set
Classifier: Development Status :: 3 - Alpha
Classifier: Intended Audience :: Developers
Classifier: Topic :: Software Development :: Libraries :: Python Modules
Classifier: License :: OSI Approved :: MIT License
Classifier: Programming Language :: Python :: 3.9
Classifier: Programming Language :: Python :: 3.10
Classifier: Programming Language :: Python :: 3.11
License-File: LICENSE
Requires-Dist: accelerate <1.0.0,>=0.21.0
Requires-Dist: anthropic >=0.25.7
Requires-Dist: Cython >=0.29.35
Requires-Dist: datasets >=2.12.0
Requires-Dist: evaluate ==0.4.2
Requires-Dist: fastapi ==0.110.2
Requires-Dist: faiss-cpu >=1.8.0
Requires-Dist: ipywidgets ==7.7.1
Requires-Dist: joblib <2.0.0,>=1.2.0
Requires-Dist: matplotlib <4.0.0,>=3.7.1
Requires-Dist: matplotlib-inline <0.2.0,>=0.1.6
Requires-Dist: nltk <4.0.0,>=3.8.1
Requires-Dist: numexpr <3.0.0,>=2.8.4
Requires-Dist: numpy <2.0.0,>=1.20.0
Requires-Dist: openai ==1.14.2
Requires-Dist: pandas >=2.0.1
Requires-Dist: python-dateutil <3.0.0,>=2.8.2
Requires-Dist: pytorch-ranger <0.2.0,>=0.1.1
Requires-Dist: pytz <2024.0,>=2023.3
Requires-Dist: PyYAML <7.0,>=6.0
Requires-Dist: requests <3.0.0,>=2.25.1
Requires-Dist: scikit-learn <1.3.0,>=1.2.2
Requires-Dist: scipy <1.11.0,>=1.10.1
Requires-Dist: sentencepiece ==0.1.99
Requires-Dist: sentence-transformers <3.0.0,>=2.2.2
Requires-Dist: spacy <4.0.0,>=3.5.3
Requires-Dist: torch >=2.2.1
Requires-Dist: together >=1.1.0
Requires-Dist: tokenizers >=0.13.3
Requires-Dist: transformers ==4.40.1
Provides-Extra: vllm
Requires-Dist: vllm ==0.4.1 ; extra == 'vllm'
